backlog/__init__.py
backlog/prefs.py
backlog/schema.py
backlog/web_ui.py
backlog/htdocs/css/backlog.css
backlog/htdocs/js/dijit/CheckedMenuItem.js
backlog/htdocs/js/dijit/Menu.js
backlog/htdocs/js/dijit/MenuItem.js
backlog/htdocs/js/dijit/MenuSeparator.js
backlog/htdocs/js/dijit/PopupMenuItem.js
backlog/htdocs/js/dijit/_Contained.js
backlog/htdocs/js/dijit/_Container.js
backlog/htdocs/js/dijit/_KeyNavContainer.js
backlog/htdocs/js/dijit/_Templated.js
backlog/htdocs/js/dijit/_Widget.js
backlog/htdocs/js/dijit/_base.js
backlog/htdocs/js/dijit/dijit.js
backlog/htdocs/js/dijit/_base/focus.js
backlog/htdocs/js/dijit/_base/manager.js
backlog/htdocs/js/dijit/_base/place.js
backlog/htdocs/js/dijit/_base/popup.js
backlog/htdocs/js/dijit/_base/scroll.js
backlog/htdocs/js/dijit/_base/sniff.js
backlog/htdocs/js/dijit/_base/typematic.js
backlog/htdocs/js/dijit/_base/wai.js
backlog/htdocs/js/dijit/_base/window.js
backlog/htdocs/js/dijit/themes/dijit.css
backlog/htdocs/js/dijit/themes/tundra/tundra.css
backlog/htdocs/js/dijit/themes/tundra/images/spriteArrows.png
backlog/htdocs/js/dojo/AdapterRegistry.js
backlog/htdocs/js/dojo/NodeList-fx.js
backlog/htdocs/js/dojo/dojo.js
backlog/htdocs/js/dojo/fx.js
backlog/htdocs/js/dojo/parser.js
backlog/htdocs/js/dojo/string.js
backlog/htdocs/js/dojo/date/stamp.js
backlog/htdocs/js/dojo/dnd/Avatar.js
backlog/htdocs/js/dojo/dnd/Container.js
backlog/htdocs/js/dojo/dnd/Manager.js
backlog/htdocs/js/dojo/dnd/Selector.js
backlog/htdocs/js/dojo/dnd/Source.js
backlog/htdocs/js/dojo/dnd/autoscroll.js
backlog/htdocs/js/dojo/dnd/common.js
backlog/htdocs/js/dojo/fx/Toggler.js
backlog/htdocs/js/dojo/fx/easing.js
backlog/htdocs/js/dojo/resources/blank.gif
backlog/templates/backlog.html
backlog/templates/prefs_backlog.html
TracBacklog-0.5.1.dev1.dist-info/LICENSE.txt
TracBacklog-0.5.1.dev1.dist-info/METADATA
TracBacklog-0.5.1.dev1.dist-info/WHEEL
TracBacklog-0.5.1.dev1.dist-info/entry_points.txt
TracBacklog-0.5.1.dev1.dist-info/top_level.txt
TracBacklog-0.5.1.dev1.dist-info/RECORD
