Metadata-Version: 2.1
Name: TracBacklog
Version: 0.5.1.dev1
Summary: Enables Trac to be used for managing your ticket backlog.
Home-page: https://github.com/trac-hacks/trac-backlog
Author: John Szakmeister
Author-email: john@szakmeister.net
Maintainer: Theodor Norup
Maintainer-email: theodor.norup@gmail.com
License: BSD
Platform: UNKNOWN
Classifier: Development Status :: 4 - Beta
Classifier: Environment :: Plugins
Classifier: Environment :: Web Environment
Classifier: Framework :: Trac
Classifier: Intended Audience :: Developers
Classifier: Intended Audience :: System Administrators
Classifier: License :: OSI Approved :: BSD License
Classifier: Natural Language :: English
Classifier: Operating System :: OS Independent
Classifier: Programming Language :: Python :: 2 :: Only
Requires-Dist: simplejson (>=2.0)
